url_to_book/__init__.py
url_to_book/cli.py
url_to_book/extractor.py
url_to_book/image_handler.py
url_to_book/progress.py
url_to_book/state_machine.py
url_to_book/renderers/__init__.py
url_to_book/renderers/base.py
url_to_book/renderers/converter.py
url_to_book/renderers/document.py
url_to_book/renderers/epub_renderer.py
url_to_book/renderers/fb2_renderer.py
url_to_book/renderers/markdown_parser.py
url_to_book/renderers/markdown_renderer.py
url_to_book/renderers/pdf_renderer.py
url_to_book/renderers/registry.py
url_to_book-1.0.0.dist-info/licenses/LICENSE
url_to_book-1.0.0.dist-info/METADATA
url_to_book-1.0.0.dist-info/WHEEL
url_to_book-1.0.0.dist-info/entry_points.txt
url_to_book-1.0.0.dist-info/top_level.txt
url_to_book-1.0.0.dist-info/RECORD
