Metadata-Version: 2.4
Name: url_to_book
Version: 1.0.0
Summary: CLI tool to convert web articles to PDF, EPUB, FB2, and Markdown
Author: Roman Averin
License: MIT
Project-URL: Homepage, https://github.com/RomanAverin/url_to_book
Project-URL: Repository, https://github.com/RomanAverin/url_to_book
Project-URL: Issues, https://github.com/RomanAverin/url_to_book/issues
Project-URL: Documentation, https://github.com/RomanAverin/url_to_book#readme
Project-URL: Changelog, https://github.com/RomanAverin/url_to_book/releases
Keywords: pdf,epub,fb2,markdown,converter,web-scraping,article-extraction,newspaper,ebook,ebooks,cli-tool,content-extraction,web-to-pdf
Classifier: Development Status :: 5 - Production/Stable
Classifier: Intended Audience :: Developers
Classifier: Intended Audience :: End Users/Desktop
Classifier: Intended Audience :: Information Technology
Classifier: Topic :: Internet :: WWW/HTTP
Classifier: Topic :: Text Processing :: Markup :: Markdown
Classifier: Topic :: Text Processing :: Markup :: HTML
Classifier: Topic :: Utilities
Classifier: Topic :: Software Development :: Libraries :: Python Modules
Classifier: License :: OSI Approved :: MIT License
Classifier: Operating System :: OS Independent
Classifier: Programming Language :: Python :: 3
Classifier: Programming Language :: Python :: 3.10
Classifier: Programming Language :: Python :: 3.11
Classifier: Programming Language :: Python :: 3.12
Classifier: Programming Language :: Python :: 3.13
Classifier: Programming Language :: Python :: 3.14
Classifier: Programming Language :: Python :: 3 :: Only
Classifier: Environment :: Console
Classifier: Natural Language :: English
Classifier: Natural Language :: Russian
Classifier: Typing :: Typed
Requires-Python: >=3.10
License-File: LICENSE
Requires-Dist: newspaper4k>=0.9.0
Requires-Dist: fpdf2>=2.7.0
Requires-Dist: click>=8.0.0
Requires-Dist: requests>=2.28.0
Requires-Dist: Pillow>=9.0.0
Requires-Dist: lxml>=4.9.0
Requires-Dist: lxml_html_clean>=0.1.0
Requires-Dist: rich>=13.0.0
Requires-Dist: ebooklib>=0.18
Requires-Dist: pyyaml>=6.0
Provides-Extra: dev
Requires-Dist: pytest>=7.0.0; extra == "dev"
Requires-Dist: pytest-cov>=4.0.0; extra == "dev"
Requires-Dist: pylint>=3.0.0; extra == "dev"
Dynamic: license-file
